{
    "name": "FLUX MOB",
    "description": "Welcome to the Flux Mob NFT Collection – a unique compilation of fantastic characters from a distant universe, embodied in the form of NFTs. In this collection, you will discover an exciting world where heroic beings, led by the powerful Elizabeth, embark on missions to extract flux crystals on a mysterious planet.",
    "image": "https://flux-ton.io/gg/ggava.png",
    "cover_image": "https://flux-ton.io/gg/ggbg.png",
    "social_links": [
        "https://t.me/flux_robot",
        "https://t.me/fluxjetton",
        "https://t.me/fluxenglang",
        "https://x.com/fluxjetton",
        "https://flux-ton.io"
    ]
}
